stac_info/__init__.py
stac_info/constants.py
stac_info/search.py
stac_info-0.0.2.dist-info/LICENSE
stac_info-0.0.2.dist-info/METADATA
stac_info-0.0.2.dist-info/WHEEL
stac_info-0.0.2.dist-info/top_level.txt
stac_info-0.0.2.dist-info/RECORD
